ofself/__init__.py
ofself/auth.py
ofself/client.py
ofself/exceptions.py
ofself/py.typed
ofself/types.py
ofself/resources/__init__.py
ofself/resources/audit.py
ofself/resources/auth.py
ofself/resources/authorizations.py
ofself/resources/embeddings.py
ofself/resources/exposure_profiles.py
ofself/resources/files.py
ofself/resources/follows.py
ofself/resources/graph.py
ofself/resources/history.py
ofself/resources/nodes.py
ofself/resources/proposals.py
ofself/resources/relationships.py
ofself/resources/sharing.py
ofself/resources/tags.py
ofself/resources/third_party.py
ofself/resources/users.py
ofself/resources/webhooks.py
ofself-0.1.0.dist-info/METADATA
ofself-0.1.0.dist-info/WHEEL
ofself-0.1.0.dist-info/licenses/LICENSE
ofself-0.1.0.dist-info/RECORD
