Metadata-Version: 2.4
Name: ofself
Version: 0.1.0
Summary: Official Python SDK for the OfSelf API - Personal data sovereignty platform
Project-URL: Homepage, https://ofself.ai
Project-URL: Documentation, https://docs.ofself.ai
Project-URL: Repository, https://github.com/ofself/ofself-sdk-python
Project-URL: Changelog, https://github.com/ofself/ofself-sdk-python/blob/main/CHANGELOG.md
Author-email: OfSelf Team <dev@ofself.ai>
License-Expression: MIT
License-File: LICENSE
Keywords: api,data-sovereignty,ofself,personal-data,privacy,sdk
Classifier: Development Status :: 4 - Beta
Classifier: Intended Audience :: Developers
Classifier: License :: OSI Approved :: MIT License
Classifier: Operating System :: OS Independent
Classifier: Programming Language :: Python :: 3
Classifier: Programming Language :: Python :: 3.8
Classifier: Programming Language :: Python :: 3.9
Classifier: Programming Language :: Python :: 3.10
Classifier: Programming Language :: Python :: 3.11
Classifier: Programming Language :: Python :: 3.12
Classifier: Topic :: Software Development :: Libraries :: Python Modules
Classifier: Typing :: Typed
Requires-Python: >=3.8
Requires-Dist: httpx>=0.24.0
Requires-Dist: pydantic>=2.0.0
Provides-Extra: dev
Requires-Dist: black>=23.0.0; extra == 'dev'
Requires-Dist: isort>=5.12.0; extra == 'dev'
Requires-Dist: mypy>=1.0.0; extra == 'dev'
Requires-Dist: pytest-asyncio>=0.21.0; extra == 'dev'
Requires-Dist: pytest-cov>=4.0.0; extra == 'dev'
Requires-Dist: pytest>=7.0.0; extra == 'dev'
Requires-Dist: respx>=0.20.0; extra == 'dev'
Requires-Dist: ruff>=0.1.0; extra == 'dev'
